{
  "SelectedAuto": "StartCenter",
  "TrenchStart": {
    "SelectedField": "Field2020",
    "xPosInit": 7.3,
    "yPosInit": 3.3,
    "autoCSVPath": "/resources/trenchStealTwoShootFiveAuto.csv"
  },
  "StartCenter": {
    "SelectedField": "BarrelRacing",
    "xPosInit": 2.5,
    "yPosInit": 3.3,
    "autoCSVPath": "/resources/startCenterFriendlyTrenchThreeShootThreeAuto.csv"
  },

  "BarrelRacing": {
    "SelectedField": "BarrelRacing",
    "xPosInit": 2.5,
    "yPosInit": 3.3,
    "autoCSVPath": "/resources/barrelRacing.csv"
  },
  "Bounce": {
    "SelectedField": "Bounce",
    "xPosInit": 2.5,
    "yPosInit": 3.3,
    "autoCSVPath": "/resources/bounce.csv"
  },
  "GalacticSearchA": {
    "SelectedField": "GalacticSearchA",
    "xPosInit": 2.5,
    "yPosInit": 3.3,
    "autoCSVPath": "/resources/galacticSearchA.csv"
  },
  "GalacticSearchB": {
    "SelectedField": "GalacticSearchB",
    "xPosInit": 2.5,
    "yPosInit": 3.3,
    "autoCSVPath": "/resources/galacticSearchB.csv"
  },
  "Slalom": {
    "SelectedField": "Slalom",
    "xPosInit": 2.5,
    "yPosInit": 3.3,
    "autoCSVPath": "/resources/slalom.csv"
  }
}
